medicio/__init__.py
medicio/apps.py
medicio/sitemaps.py
medicio/urls.py
medicio/views.py
medicio/static/medicio/css/style.css
medicio/static/medicio/js/main.js
medicio/static/medicio/scss/_footer.scss
medicio/static/medicio/scss/_general.scss
medicio/static/medicio/scss/_header.scss
medicio/static/medicio/scss/_hero.scss
medicio/static/medicio/scss/_nav.scss
medicio/static/medicio/scss/_sections.scss
medicio/static/medicio/scss/_variables.scss
medicio/static/medicio/scss/style.scss
medicio/static/medicio/vendor/animate.css/animate.compat.css
medicio/static/medicio/vendor/animate.css/animate.css
medicio/static/medicio/vendor/animate.css/animate.min.css
medicio/static/medicio/vendor/aos/aos.cjs.js
medicio/static/medicio/vendor/aos/aos.css
medicio/static/medicio/vendor/aos/aos.esm.js
medicio/static/medicio/vendor/aos/aos.js
medicio/static/medicio/vendor/aos/aos.js.map
medicio/static/medicio/vendor/bootstrap/css/bootstrap-grid.css
medicio/static/medicio/vendor/bootstrap/css/bootstrap-grid.css.map
medicio/static/medicio/vendor/bootstrap/css/bootstrap-grid.min.css
medicio/static/medicio/vendor/bootstrap/css/bootstrap-grid.min.css.map
medicio/static/medicio/vendor/bootstrap/css/bootstrap-grid.rtl.css
medicio/static/medicio/vendor/bootstrap/css/bootstrap-grid.rtl.css.map
medicio/static/medicio/vendor/bootstrap/css/bootstrap-grid.rtl.min.css
medicio/static/medicio/vendor/bootstrap/css/bootstrap-grid.rtl.min.css.map
medicio/static/medicio/vendor/bootstrap/css/bootstrap-reboot.css
medicio/static/medicio/vendor/bootstrap/css/bootstrap-reboot.css.map
medicio/static/medicio/vendor/bootstrap/css/bootstrap-reboot.min.css
medicio/static/medicio/vendor/bootstrap/css/bootstrap-reboot.min.css.map
medicio/static/medicio/vendor/bootstrap/css/bootstrap-reboot.rtl.css
medicio/static/medicio/vendor/bootstrap/css/bootstrap-reboot.rtl.css.map
medicio/static/medicio/vendor/bootstrap/css/bootstrap-reboot.rtl.min.css
medicio/static/medicio/vendor/bootstrap/css/bootstrap-reboot.rtl.min.css.map
django_medicio_dental-5.3.0.dist-info/WHEEL
django_medicio_dental-5.3.0.dist-info/METADATA
django_medicio_dental-5.3.0.dist-info/RECORD
