Metadata-Version: 2.3
Name: django_medicio_dental
Version: 5.3.0
Summary: Demiansoft template(medicio)
Requires-Python: >=3.6
Requires-Dist: Django>=4.2.11
Requires-Dist: shared_lib_ds>=1.5.0
